{
  "id": "2026-06-26-airline-close-calls",
  "date": "2026-06-26",
  "level": "B1-",
  "nextLevel": "B1（中級）",
  "title": "Airline Group Warns of Close Calls",
  "source": {
    "type": "youtube-news",
    "title": "Airline organization leader warns of 'hundreds' of close calls every day",
    "channel": "NBC News",
    "url": "https://www.youtube.com/watch?v=0ezh1Ea8xog"
  },
  "tags": [
    "YouTube 英文新聞聽力",
    "NBC News / aviation safety",
    "交通同安全科技",
    "字幕對齊聽力",
    "日常美式口語",
    "詞數：約74",
    "練習時間：約8分鐘",
    "daily-life speaking：約5分鐘"
  ],
  "methodSteps": [
    "盲聽",
    "看稿",
    "拆解",
    "重聽",
    "跟讀"
  ],
  "segments": [
    {
      "title": "Recent Close Call",
      "time": "00:05",
      "audioText": "The most recent close call happened this weekend.",
      "transcript": "The most recent close call happened this weekend.",
      "translationZh": "最近一次險些出事嘅情況就喺今個週末發生。",
      "points": [
        {
          "label": "The most recent",
          "explanationZh": "most recent 即最近一次；新聞常用嚟帶出最新例子。"
        },
        {
          "label": "close call",
          "explanationZh": "close call 係差啲出事、險些釀成事故。"
        },
        {
          "label": "happened this weekend",
          "explanationZh": "happened 接時間，快速交代事件幾時發生。"
        }
      ]
    },
    {
      "title": "Landing Aborted",
      "time": "00:08",
      "audioText": "Confusion as a Delta flight aborted its landing in Boston after a cockpit collision alert warned that an American jet was just 300 feet away on an intersecting runway.",
      "transcript": "Confusion as a Delta flight aborted its landing in Boston after a cockpit collision alert warned that an American jet was just 300 feet away on an intersecting runway.",
      "translationZh": "一班達美航班喺波士頓中止降落，因為駕駛艙防撞警報提醒，一架美航客機喺交叉跑道上只相距 300 呎，場面一度混亂。",
      "points": [
        {
          "label": "aborted its landing",
          "explanationZh": "aborted 係中止；aborted its landing 即取消原本嘅降落動作。"
        },
        {
          "label": "a cockpit collision alert",
          "explanationZh": "cockpit 係駕駛艙；collision alert 係防撞警報。"
        },
        {
          "label": "just 300 feet away",
          "explanationZh": "just 加數字強調距離好近；聽數字時先抓 300，再聽 feet away。"
        },
        {
          "label": "on an intersecting runway",
          "explanationZh": "intersecting runway 係交叉跑道，兩條路線有交會位。"
        }
      ]
    },
    {
      "title": "A Stunning Revelation",
      "time": "00:25",
      "audioText": "Today, a stunning revelation from the organization that represents the nation's airlines.",
      "transcript": "Today, a stunning revelation from the organization that represents the nation's airlines.",
      "translationZh": "今日，代表全國航空公司嘅組織披露咗一項令人震驚嘅消息。",
      "points": [
        {
          "label": "a stunning revelation",
          "explanationZh": "stunning 係令人震驚；revelation 係披露或揭示出嚟嘅消息。"
        },
        {
          "label": "the organization that represents",
          "explanationZh": "that represents 後面解釋呢個組織代表邊一方。"
        },
        {
          "label": "the nation's airlines",
          "explanationZh": "nation's airlines 即全國航空公司，新聞用 nation's 令語氣更正式。"
        }
      ]
    },
    {
      "title": "FAA Response",
      "time": "00:48",
      "audioText": "The FAA says most reported incidents are not close calls and that runway incursion rates have decreased more than 10% since last year.",
      "transcript": "The FAA says most reported incidents are not close calls and that runway incursion rates have decreased more than 10% since last year.",
      "translationZh": "FAA 表示，大部分通報事件並唔係險些相撞，而且跑道入侵率自去年以嚟已下降超過 10%。",
      "points": [
        {
          "label": "most reported incidents",
          "explanationZh": "reported incidents 係已通報事件；most 表示大部分。"
        },
        {
          "label": "are not close calls",
          "explanationZh": "are not 用嚟澄清分類，唔係所有通報都等於差啲出事。"
        },
        {
          "label": "have decreased more than 10%",
          "explanationZh": "have decreased 表示已經下降；more than 10% 即超過百分之十。"
        }
      ]
    },
    {
      "title": "Receivers on Planes",
      "time": "01:16",
      "audioText": "The pilots union and NTSB want Congress to require all planes to have precise GPS-based air traffic receivers that show surrounding air traffic.",
      "transcript": "The pilots union and NTSB want Congress to require all planes to have precise GPS-based air traffic receivers that show surrounding air traffic.",
      "translationZh": "機師工會同 NTSB 希望國會要求所有飛機配備精準嘅 GPS 航空交通接收器，顯示周圍嘅空中交通。",
      "points": [
        {
          "label": "want Congress to require",
          "explanationZh": "want A to do B 係希望 A 做某事；require 即規定、要求。"
        },
        {
          "label": "precise GPS-based",
          "explanationZh": "precise 係精準；GPS-based 即以 GPS 技術為基礎。"
        },
        {
          "label": "show surrounding air traffic",
          "explanationZh": "surrounding air traffic 即附近其他飛機嘅空中交通狀況。"
        }
      ]
    }
  ],
  "sentences": [
    "The most recent close call happened this weekend.",
    "Confusion as a Delta flight aborted its landing in Boston after a cockpit collision alert warned that an American jet was just 300 feet away on an intersecting runway.",
    "Today, a stunning revelation from the organization that represents the nation's airlines.",
    "The FAA says most reported incidents are not close calls and that runway incursion rates have decreased more than 10% since last year.",
    "The pilots union and NTSB want Congress to require all planes to have precise GPS-based air traffic receivers that show surrounding air traffic."
  ],
  "vocabulary": [
    {
      "word": "aviation",
      "ipa": "/ˌeɪ.viˈeɪ.ʃən/",
      "partOfSpeech": "noun",
      "meaningZh": "航空；航空業",
      "example": "Aviation safety is a major topic for travelers.",
      "translationZh": "航空安全係旅客好關心嘅主題。",
      "mastery": 2,
      "nextReview": "明天"
    },
    {
      "word": "abort",
      "ipa": "/əˈbɔːrt/",
      "partOfSpeech": "verb",
      "meaningZh": "中止；取消原本動作",
      "example": "The pilot had to abort the landing.",
      "translationZh": "機師需要中止降落。",
      "mastery": 2,
      "nextReview": "明天"
    },
    {
      "word": "collision",
      "ipa": "/kəˈlɪʒ.ən/",
      "partOfSpeech": "noun",
      "meaningZh": "碰撞；相撞",
      "example": "The alert warned of a possible collision.",
      "translationZh": "警報提醒可能會相撞。",
      "mastery": 2,
      "nextReview": "明天"
    },
    {
      "word": "revelation",
      "ipa": "/ˌrev.əˈleɪ.ʃən/",
      "partOfSpeech": "noun",
      "meaningZh": "披露；揭示嘅消息",
      "example": "The report included a surprising revelation.",
      "translationZh": "報告入面有一項令人意外嘅披露。",
      "mastery": 2,
      "nextReview": "明天"
    },
    {
      "word": "incident",
      "ipa": "/ˈɪn.sɪ.dənt/",
      "partOfSpeech": "noun",
      "meaningZh": "事件；事故",
      "example": "Officials reviewed the incident at the airport.",
      "translationZh": "官員檢視咗機場嗰宗事件。",
      "mastery": 2,
      "nextReview": "明天"
    },
    {
      "word": "require",
      "ipa": "/rɪˈkwaɪr/",
      "partOfSpeech": "verb",
      "meaningZh": "規定；要求",
      "example": "The rule may require new safety equipment.",
      "translationZh": "呢條規則可能會要求新安全設備。",
      "mastery": 2,
      "nextReview": "明天"
    },
    {
      "word": "surrounding",
      "ipa": "/səˈraʊn.dɪŋ/",
      "partOfSpeech": "adjective",
      "meaningZh": "周圍嘅；附近嘅",
      "example": "The screen shows surrounding traffic.",
      "translationZh": "個螢幕會顯示附近交通。",
      "mastery": 2,
      "nextReview": "明天"
    }
  ],
  "phrases": [
    {
      "phrase": "the most recent close call",
      "meaningZh": "最近一次險些出事嘅情況",
      "example": "The most recent close call happened at a busy airport."
    },
    {
      "phrase": "aborted its landing",
      "meaningZh": "中止降落",
      "example": "The plane aborted its landing after an alert."
    },
    {
      "phrase": "a stunning revelation",
      "meaningZh": "一項令人震驚嘅披露",
      "example": "The hearing brought a stunning revelation."
    },
    {
      "phrase": "reported incidents",
      "meaningZh": "已通報事件",
      "example": "Most reported incidents were reviewed by officials."
    },
    {
      "phrase": "surrounding air traffic",
      "meaningZh": "附近空中交通",
      "example": "The system shows surrounding air traffic."
    }
  ],
  "speakingPractice": [
    {
      "type": "shadowing",
      "instructionZh": "由 00:05 跟讀 The most recent close call...，留意 close call 兩個字連住讀。"
    },
    {
      "type": "dictation",
      "instructionZh": "重播 00:08，先聽寫 aborted its landing，再補 just 300 feet away on an intersecting runway。"
    },
    {
      "type": "substitution",
      "instructionZh": "用 The FAA says... 練替換：The company says... / The airport says... / The report says..."
    },
    {
      "type": "retelling",
      "instructionZh": "用兩句英文複述：NBC reported a recent close call in Boston. Some aviation groups want more GPS-based safety equipment."
    }
  ],
  "notes": [
    "今日片段係 NBC News 約 1 至 2 分鐘嘅航空安全新聞，旁白由 Tom Costello 報道，主題係飛機近距離險情同安全科技。",
    "聽力重點係航空新聞常見表達：close call、aborted its landing、collision alert、reported incidents、require all planes to have。",
    "時間碼 00:05、00:08、00:25、00:48、01:16 可以逐句重播；先盲聽事件動詞，再看稿拆成短 chunk。",
    "dailyLifePractice 會延伸到機場問延誤、改約時間同向同事解釋安全提醒，練自然美式日常口語。"
  ],
  "dailyLifePractice": [
    {
      "title": "Asking at the Gate",
      "contextZh": "場景：你喺機場見到登機口有延誤通知，想禮貌問職員最新情況。",
      "audioText": "Hi, do you have any update on this flight? Is the gate still the same? Thanks, I'll keep an eye on the board.",
      "lines": [
        {
          "speaker": "You",
          "en": "Hi, do you have any update on this flight?",
          "zh": "你好，請問呢班機有冇最新消息？"
        },
        {
          "speaker": "Agent",
          "en": "We're waiting for one more update from operations.",
          "zh": "我哋仲等緊營運部門一個最新消息。"
        },
        {
          "speaker": "You",
          "en": "Is the gate still the same?",
          "zh": "登機口仲係同一個嗎？"
        },
        {
          "speaker": "You",
          "en": "Thanks, I'll keep an eye on the board.",
          "zh": "唔該，我會留意顯示屏。"
        }
      ],
      "nativeNoteZh": "Do you have any update on...? 好自然又有禮貌，適合問航班、預約、維修進度。keep an eye on the board 即留意顯示屏，喺機場好實用。",
      "drills": [
        {
          "label": "Substitution",
          "prompt": "將 this flight 換成 boarding、the delay 或 the gate change。",
          "example": "Do you have any update on boarding?"
        },
        {
          "label": "Quick repeat",
          "prompt": "跟讀 Is the gate still the same? 三次，語氣保持友善。",
          "example": "Is the gate still the same?"
        }
      ]
    },
    {
      "title": "Explaining a Small Delay",
      "contextZh": "場景：交通或航班有少少阻滯，你想快速通知朋友可能遲到。",
      "audioText": "Quick heads-up: my flight is running late. I might get there about fifteen minutes later than planned. Thanks for being flexible.",
      "lines": [
        {
          "speaker": "You",
          "en": "Quick heads-up: my flight is running late.",
          "zh": "提提你：我班機有啲延誤。"
        },
        {
          "speaker": "Friend",
          "en": "No worries. Thanks for letting me know.",
          "zh": "唔緊要，多謝你通知我。"
        },
        {
          "speaker": "You",
          "en": "I might get there about fifteen minutes later than planned.",
          "zh": "我可能會比原定遲大約十五分鐘到。"
        },
        {
          "speaker": "You",
          "en": "Thanks for being flexible.",
          "zh": "多謝你咁彈性配合。"
        }
      ],
      "nativeNoteZh": "Quick heads-up 係好自然嘅『先通知你一聲』。Thanks for being flexible 比淨係講 sorry 更正面，適合輕微改時間。",
      "drills": [
        {
          "label": "Polite rephrase",
          "prompt": "用 I might get there about... later than planned 講一個遲到時間。",
          "example": "I might get there about ten minutes later than planned."
        },
        {
          "label": "Short response practice",
          "prompt": "對方話 No worries，你用一句英文表示感謝。",
          "example": "Thanks for being flexible."
        }
      ]
    },
    {
      "title": "Safety Reminder at Work",
      "contextZh": "場景：工作上有新安全提醒，你想用簡短自然英文同同事確認。",
      "audioText": "Just a quick reminder: please double-check the equipment before you start. If anything looks off, let me know right away.",
      "lines": [
        {
          "speaker": "You",
          "en": "Just a quick reminder: please double-check the equipment before you start.",
          "zh": "提一提：開始之前請再檢查一次設備。"
        },
        {
          "speaker": "Coworker",
          "en": "Got it. I'll take a look now.",
          "zh": "收到，我而家睇一睇。"
        },
        {
          "speaker": "You",
          "en": "If anything looks off, let me know right away.",
          "zh": "如果有任何嘢唔妥，即刻話我知。"
        },
        {
          "speaker": "Coworker",
          "en": "Will do.",
          "zh": "會，冇問題。"
        }
      ],
      "nativeNoteZh": "looks off 係美式口語，意思係睇落唔太對路。Will do 係簡短自然嘅回覆，表示『我會照做』。",
      "drills": [
        {
          "label": "Substitution",
          "prompt": "將 the equipment 換成 the schedule、the address 或 the form。",
          "example": "Please double-check the address before you start."
        },
        {
          "label": "Say-it-your-way",
          "prompt": "用 If anything looks off... 講一個安全提醒。",
          "example": "If anything looks off, call me before you continue."
        }
      ]
    }
  ]
}
